core/__init__.py
core/admin.py
core/apps.py
core/models.py
core/runner.py
core/storage.py
core/tests.py
core/urls.py
core/views.py
core/BO/__init__.py
core/BO/integracao.py
core/api/__init__.py
core/api/admin.py
core/api/apps.py
core/api/models.py
core/api/tests.py
core/api/views.py
core/api/migrations/0001_initial.py
core/api/migrations/0002_auto_20200824_1521.py
core/api/migrations/__init__.py
core/cliente/__init__.py
core/cliente/admin.py
core/cliente/apps.py
core/cliente/models.py
core/cliente/tests.py
core/cliente/urls.py
core/cliente/views.py
core/cliente/BO/__init__.py
core/cliente/migrations/0001_initial.py
core/cliente/migrations/0002_auto_20200713_0030.py
core/cliente/migrations/0003_auto_20200715_1925.py
core/cliente/migrations/0004_auto_20200716_1205.py
core/cliente/migrations/0005_auto_20200716_1347.py
core/cliente/migrations/0006_auto_20200716_1413.py
core/cliente/migrations/0007_auto_20200716_1451.py
core/cliente/migrations/0008_remove_endereco_cep.py
core/cliente/migrations/0009_endereco_cep.py
core/cliente/migrations/0010_auto_20200720_1146.py
core/cliente/migrations/0011_auto_20200728_1233.py
core/cliente/migrations/0012_auto_20200728_1310.py
core/cliente/migrations/0013_auto_20200728_1402.py
core/cliente/migrations/0014_auto_20200728_1413.py
core/cliente/migrations/0015_termo_ordem.py
core/cliente/migrations/0016_auto_20200728_1524.py
core/cliente/migrations/0017_auto_20200728_1525.py
core/cliente/migrations/0018_auto_20200728_1746.py
core/cliente/migrations/0019_auto_20200728_1752.py
core/cliente/migrations/0020_auto_20200729_1352.py
core/cliente/migrations/0021_auto_20200731_1612.py
core/cliente/migrations/0022_auto_20200803_1608.py
core/cliente/migrations/0023_cartao_is_principal.py
core/cliente/migrations/0024_cartao_cartao_id.py
core/cliente/migrations/0025_cliente_imagem.py
core/cliente/migrations/0026_auto_20200805_1705.py
core/cliente/migrations/0027_auto_20200806_1830.py
core/cliente/migrations/0028_auto_20200806_2317.py
django_inteliger-0.1.71.dist-info/LICENSE
django_inteliger-0.1.71.dist-info/METADATA
django_inteliger-0.1.71.dist-info/WHEEL
django_inteliger-0.1.71.dist-info/top_level.txt
django_inteliger-0.1.71.dist-info/RECORD
