Metadata-Version: 2.1
Name: django-inteliger
Version: 0.1.71
Summary: Aplicativos base para seu projeto django!
Home-page: https://www.inteliger.com.br/
Author: Inteliger
Author-email: contato@inteliger.com.br
License: BSD-3-Clause
Platform: UNKNOWN
Classifier: Environment :: Web Environment
Classifier: Framework :: Django
Classifier: Intended Audience :: Developers
Classifier: License :: OSI Approved :: BSD License
Classifier: Operating System :: OS Independent
Classifier: Programming Language :: Python :: 3.7
Classifier: Topic :: Internet :: WWW/HTTP
Classifier: Topic :: Internet :: WWW/HTTP :: Dynamic Content
Requires-Dist: django (==2.1.7)
Requires-Dist: requests
Requires-Dist: django-user-agents
Requires-Dist: django-composite-foreignkey
Requires-Dist: cryptography
